git_pptx/__init__.py
git_pptx/__main__.py
git_pptx-0.1.0.dist-info/WHEEL
git_pptx-0.1.0.dist-info/entry_points.txt
git_pptx-0.1.0.dist-info/METADATA
git_pptx-0.1.0.dist-info/RECORD
