Metadata-Version: 2.1
Name: git-pptx
Version: 0.1.0
Summary: Store .pptx slides on Git as plain text files
License: MIT
Author: Antonio Feregrino
Author-email: antonio.feregrino@gmail.com
Requires-Python: >=3.8,<4.0
Classifier: License :: OSI Approved :: MIT License
Classifier: Programming Language :: Python :: 3
Classifier: Programming Language :: Python :: 3.8
Classifier: Programming Language :: Python :: 3.9
Classifier: Programming Language :: Python :: 3.10
Classifier: Programming Language :: Python :: 3.11
Requires-Dist: click (>=8.1.3,<9.0.0)
